<Objects>
    <Defect rallyAPIMajor="1" rallyAPIMinor="36" ref="https://rally1.rallydev.com/slm/webservice/x/defect/6538459142" objectVersion="23" refObjectName="Better exception handling for a few cases" CreatedAt="May 29">
        <CreationDate>2012-05-29T13:11:37.685Z</CreationDate>
        <ObjectID>6538459142</ObjectID>
        <Subscription rallyAPIMajor="1" rallyAPIMinor="36" ref="https://rally1.rallydev.com/slm/webservice/x/subscription/4211763183" refObjectName="Bill &amp; Melinda Gates Foundation - DC" type="Subscription" />
        <Workspace rallyAPIMajor="1" rallyAPIMinor="36" ref="https://rally1.rallydev.com/slm/webservice/x/workspace/4211763192" refObjectName="SLI Workspace" type="Workspace" />
        <Changesets />
        <Description>In the ingestion catalina/jetty logs, I see the follow during the running of the negative acceptance tests:       &lt;div&gt;&lt;br /&gt;&lt;/div&gt;  &lt;div&gt;  &lt;div&gt;[Fatal Error] :-1:-1: Premature end of file.&lt;/div&gt;  &lt;div&gt;[Fatal Error] :31:4: The element type "Name" must be terminated by the matching end-tag "&amp;lt;/Name&amp;gt;".&lt;/div&gt;  &lt;div&gt;[Fatal Error] :17:5: The element type "Address" must be terminated by the matching end-tag "&amp;lt;/Address&amp;gt;".&lt;/div&gt;  &lt;/div&gt;  &lt;div&gt;&lt;br /&gt;&lt;/div&gt;  &lt;div&gt;The operators probably do not want to see the word 'Fatal' in the logs&lt;/div&gt;</Description>
        <Discussion />
        <FormattedID>DE626</FormattedID>
        <LastUpdateDate>2012-07-02T15:44:04.659Z</LastUpdateDate>
        <Name>Better exception handling for a few cases</Name>
        <Notes />
        <Owner rallyAPIMajor="1" rallyAPIMinor="36" ref="https://rally1.rallydev.com/slm/webservice/x/user/5125038442" refObjectName="Thomas Shewchuk" type="User" />
        <Project rallyAPIMajor="1" rallyAPIMinor="36" ref="https://rally1.rallydev.com/slm/webservice/x/project/4527823441" refObjectName="Galactus(Eng-NJ)" type="Project" />
        <RevisionHistory rallyAPIMajor="1" rallyAPIMinor="36" ref="https://rally1.rallydev.com/slm/webservice/x/revisionhistory/6538459143" type="RevisionHistory" />
        <Tags>
            <Tag rallyAPIMajor="1" rallyAPIMinor="36" ref="https://rally1.rallydev.com/slm/webservice/x/tag/4624169841" refObjectName="Persona:Operator" type="Tag" />
        </Tags>
        <AffectsDoc>false</AffectsDoc>
        <Attachments />
        <Blocked>false</Blocked>
        <Duplicates />
        <Environment>Development/CI</Environment>
        <OpenedDate>2012-06-21T17:12:09.581Z</OpenedDate>
        <PlanEstimate>2.0</PlanEstimate>
        <Priority>Next Interim Release (P3)</Priority>
        <Rank>499999716608.000</Rank>
        <Recycled>false</Recycled>
        <Release rallyAPIMajor="1" rallyAPIMinor="36" ref="https://rally1.rallydev.com/slm/webservice/x/release/5694780841" refObjectName="PI5" type="Release" />
        <ReleaseNote>true</ReleaseNote>
        <Resolution>None</Resolution>
        <ScheduleState>Defined</ScheduleState>
        <Severity>Minor or Aesthetic Problem (Sev4)</Severity>
        <State>Open</State>
        <SubmittedBy rallyAPIMajor="1" rallyAPIMinor="36" ref="https://rally1.rallydev.com/slm/webservice/x/user/4711866137" refObjectName="James Short" type="User" />
        <TaskActualTotal>0.0</TaskActualTotal>
        <TaskEstimateTotal>0.0</TaskEstimateTotal>
        <TaskRemainingTotal>0.0</TaskRemainingTotal>
        <TaskStatus>NONE</TaskStatus>
        <Tasks />
        <TestCaseStatus>NONE</TestCaseStatus>
        <TestCases />
        <ReleaseNoteDescription>Some logged errors may not properly reflect the severity of issues.</ReleaseNoteDescription>
    </Defect>
    <Defect rallyAPIMajor="1" rallyAPIMinor="36" ref="https://rally1.rallydev.com/slm/webservice/x/defect/7203854496" objectVersion="3" refObjectName="SLC Operator has knowledge of new super admin users' passwords" CreatedAt="Jul 19">
        <CreationDate>2012-07-19T15:45:44.298Z</CreationDate>
        <ObjectID>7203854496</ObjectID>
        <Subscription rallyAPIMajor="1" rallyAPIMinor="36" ref="https://rally1.rallydev.com/slm/webservice/x/subscription/4211763183" refObjectName="Bill &amp; Melinda Gates Foundation - DC" type="Subscription" />
        <Workspace rallyAPIMajor="1" rallyAPIMinor="36" ref="https://rally1.rallydev.com/slm/webservice/x/workspace/4211763192" refObjectName="SLI Workspace" type="Workspace" />
        <Changesets />
        <Description>This defect is related to&amp;nbsp;&amp;nbsp;US2917&amp;nbsp;&lt;a href="https://rally1.rallydev.com/#/4314775983d/detail/userstory/6789872354"&gt;https://rally1.rallydev.com/#/4314775983d/detail/userstory/6789872354&lt;/a&gt;&amp;nbsp;and US2623&amp;nbsp; &lt;a href="https://rally1.rallydev.com/#/4314775983d/detail/userstory/6514069713"&gt;https://rally1.rallydev.com/#/4314775983d/detail/userstory/6514069713&lt;/a&gt; &lt;div&gt;&lt;br /&gt;&lt;/div&gt; &lt;div&gt;When creating a new super admin, the SLC Operator must set the super admin's password in LDAP.&amp;nbsp;&lt;/div&gt; &lt;div&gt;&lt;br /&gt;&lt;/div&gt; &lt;div&gt;A corrupt operator could then log in as the user before the user has a chance to change their password. The corrupt operator could then maliciously change the user's organization's settings/configuration and access the edOrg data.&lt;/div&gt; &lt;div&gt;&lt;br /&gt;&lt;/div&gt; &lt;div&gt;The likelihood of this risk is low because it requires a corrupt operator. &amp;nbsp;The impact of this risk is high because of the potential exposure of sensitive data/PII. &amp;nbsp;Therefore the overall security severity is medium. &amp;nbsp;&lt;/div&gt; &lt;div&gt;&lt;br /&gt;&lt;/div&gt; &lt;div&gt;&lt;b&gt;Recommendation&lt;/b&gt;&lt;/div&gt; &lt;div&gt;The SAMT tool or API should generate a random password for the user rather than having the SLC Operator set the password. &amp;nbsp; &amp;nbsp;&amp;nbsp;&lt;/div&gt; &lt;div&gt;&lt;br /&gt;&lt;/div&gt; &lt;div&gt;Furthermore when the user first logs in (likely using their unique expiring one-time link sent by the account creation process), the user should be forced to change their password.&amp;nbsp;&lt;/div&gt; &lt;div&gt;&lt;br /&gt;&lt;/div&gt; &lt;div&gt;&lt;br /&gt;&lt;/div&gt;</Description>
        <Discussion />
        <FormattedID>DE1313</FormattedID>
        <LastUpdateDate>2012-07-19T21:47:19.878Z</LastUpdateDate>
        <Name>SLC Operator has knowledge of new super admin users' passwords</Name>
        <Notes />
        <Owner rallyAPIMajor="1" rallyAPIMinor="36" ref="https://rally1.rallydev.com/slm/webservice/x/user/6144897670" refObjectName="Shoichi Kikuchi" type="User" />
        <Project rallyAPIMajor="1" rallyAPIMinor="36" ref="https://rally1.rallydev.com/slm/webservice/x/project/4314775983" refObjectName="SLI" type="Project" />
        <RevisionHistory rallyAPIMajor="1" rallyAPIMinor="36" ref="https://rally1.rallydev.com/slm/webservice/x/revisionhistory/7203854497" type="RevisionHistory" />
        <Tags>
            <Tag rallyAPIMajor="1" rallyAPIMinor="36" ref="https://rally1.rallydev.com/slm/webservice/x/tag/4624169841" refObjectName="Persona:Operator" type="Tag" />
            <Tag rallyAPIMajor="1" rallyAPIMinor="36" ref="https://rally1.rallydev.com/slm/webservice/x/tag/6046945587" refObjectName="Security Defect" type="Tag" />
        </Tags>
        <AffectsDoc>false</AffectsDoc>
        <Attachments />
        <Blocked>false</Blocked>
        <Duplicates />
        <Environment>RC</Environment>
        <Priority>Emergency Release (P2)</Priority>
        <Rank>499999397376.000</Rank>
        <Recycled>false</Recycled>
        <ReleaseNote>true</ReleaseNote>
        <Resolution>None</Resolution>
        <ScheduleState>Backlog</ScheduleState>
        <Severity>Security-Medium(SEC3)</Severity>
        <State>Fixed</State>
        <SubmittedBy rallyAPIMajor="1" rallyAPIMinor="36" ref="https://rally1.rallydev.com/slm/webservice/x/user/5823891630" refObjectName="Daniel Fiedler" type="User" />
        <TaskActualTotal>0.0</TaskActualTotal>
        <TaskEstimateTotal>0.0</TaskEstimateTotal>
        <TaskRemainingTotal>0.0</TaskRemainingTotal>
        <TaskStatus>NONE</TaskStatus>
        <Tasks />
        <TestCaseStatus>NONE</TestCaseStatus>
        <TestCases />
        <ReleaseNoteDescription>&lt;style rallydeleteme="false" type="text/css"&gt;.rally-rte-class-0ae0d97c9{border-collapse: collapse; font-family: arial, helvetica, sans-serif; font-size: 11px; }.rally-rte-class-090c0c716{margin-top: 0px; margin-right: 0px; margin-bottom: 0px; margin-left: 0px; padding-top: 0px; padding-right: 0px; padding-bottom: 0px; padding-left: 0px; border-top-width: 0px; border-right-width: 0px; border-bottom-width: 0px; border-left-width: 0px; border-style: initial; border-color: initial; outline-width: 0px; outline-style: initial; outline-color: initial; font-weight: inherit; font-style: inherit; font-size: 11px; font-family: inherit; vertical-align: baseline; border-collapse: collapse; -webkit-border-horizontal-spacing: 0px; -webkit-border-vertical-spacing: 0px; background-image: initial; background-attachment: initial; background-origin: initial; background-clip: initial; background-color: rgb(255, 255, 255); border-style: initial; border-color: initial; width: 1565px; box-sizing: border-box; background-position: initial initial; background-repeat: initial initial; }.rally-rte-class-050ce70df{margin-top: 0px; margin-right: 0px; margin-bottom: 0px; margin-left: 0px; padding-top: 0px; padding-right: 0px; padding-bottom: 0px; padding-left: 0px; border-top-width: 0px; border-right-width: 0px; border-bottom-width: 0px; border-left-width: 0px; border-style: initial; border-color: initial; outline-width: 0px; outline-style: initial; outline-color: initial; font-weight: inherit; font-style: inherit; font-size: 11px; font-family: inherit; vertical-align: baseline; box-sizing: border-box; }.rally-rte-class-04b65a1cc{margin-top: 0px; margin-right: 0px; margin-bottom: 0px; margin-left: 0px; padding-top: 0px; padding-right: 0px; padding-bottom: 0px; padding-left: 0px; border-top-width: 0px; border-right-width: 0px; border-bottom-width: 0px; border-left-width: 0px; border-style: initial; border-color: initial; outline-width: 0px; outline-style: initial; outline-color: initial; font-weight: inherit; font-style: inherit; font-size: 11px; font-family: inherit; vertical-align: top; box-sizing: border-box; }.rally-rte-class-0c7b83e2f{margin-top: 0px; margin-right: 0px; margin-bottom: 0px; margin-left: 0px; padding-top: 4px; padding-right: 5px; padding-bottom: 5px; padding-left: 5px; border-top-width: 0px; border-right-width: 0px; border-bottom-width: 0px; border-left-width: 0px; border-style: initial; border-color: initial; outline-width: 0px; outline-style: initial; outline-color: initial; font-weight: normal; font-style: inherit; font-size: 12px; font-family: inherit; vertical-align: top; text-align: left; box-sizing: border-box; }.rally-rte-class-02bd3f8b1{margin-top: 0px; margin-right: 0px; margin-bottom: 0px; margin-left: 0px; padding-top: 0px; padding-right: 0px; padding-bottom: 0px; padding-left: 0px; border-top-width: 0px; border-right-width: 0px; border-bottom-width: 0px; border-left-width: 0px; border-style: initial; border-color: initial; outline-width: 0px; outline-style: initial; outline-color: initial; font-weight: inherit; font-style: inherit; font-size: 11px; font-family: arial, helvetica, sans-serif; vertical-align: baseline; box-sizing: border-box; border-collapse: collapse; }.rally-rte-class-01229557d{margin-top: 0px; margin-right: 0px; margin-bottom: 0px; margin-left: 0px; padding-top: 0px; padding-right: 0px; padding-bottom: 0px; padding-left: 0px; border-top-width: 0px; border-right-width: 0px; border-bottom-width: 0px; border-left-width: 0px; border-style: initial; border-color: initial; outline-width: 0px; outline-style: initial; outline-color: initial; font-weight: inherit; font-style: inherit; font-size: 11px; font-family: inherit; vertical-align: baseline; border-collapse: collapse; -webkit-border-horizontal-spacing: 0px; -webkit-border-vertical-spacing: 0px; background-image: initial; background-attachment: initial; background-origin: initial; background-clip: initial; background-color: rgb(255, 255, 255); border-style: initial; border-color: initial; width: 1383px; box-sizing: border-box; border-style: initial; border-color: initial; border-style: initial; border-color: initial; background-position: initial initial; background-repeat: initial initial; }.rally-rte-class-0811e915{margin-top: 0px; margin-right: 0px; margin-bottom: 0px; margin-left: 0px; padding-top: 0px; padding-right: 0px; padding-bottom: 0px; padding-left: 0px; border-top-width: 0px; border-right-width: 0px; border-bottom-width: 0px; border-left-width: 0px; border-style: initial; border-color: initial; outline-width: 0px; outline-style: initial; outline-color: initial; font-weight: inherit; font-style: inherit; font-size: 11px; font-family: inherit; vertical-align: baseline; box-sizing: border-box; border-style: initial; border-color: initial; }.rally-rte-class-03e109195{margin-top: 0px; margin-right: 0px; margin-bottom: 0px; margin-left: 0px; padding-top: 0px; padding-right: 0px; padding-bottom: 0px; padding-left: 0px; border-top-width: 0px; border-right-width: 0px; border-bottom-width: 0px; border-left-width: 0px; border-style: initial; border-color: initial; outline-width: 0px; outline-style: initial; outline-color: initial; font-weight: inherit; font-style: inherit; font-size: 11px; font-family: inherit; vertical-align: top; box-sizing: border-box; border-style: initial; border-color: initial; }.rally-rte-class-07c65e01c{margin-top: 0px; margin-right: 0px; margin-bottom: 0px; margin-left: 0px; padding-top: 4px; padding-right: 5px; padding-bottom: 5px; padding-left: 5px; border-top-width: 0px; border-right-width: 0px; border-bottom-width: 0px; border-left-width: 0px; border-style: initial; border-color: initial; outline-width: 0px; outline-style: initial; outline-color: initial; font-weight: normal; font-style: inherit; font-size: 12px; font-family: inherit; vertical-align: top; text-align: left; box-sizing: border-box; border-style: initial; border-color: initial; }.rally-rte-class-04752fe8d{margin-top: 12px; margin-right: 0px; margin-bottom: 12px; margin-left: 0px; padding-top: 0px; padding-right: 0px; padding-bottom: 0px; padding-left: 0px; border-top-width: 0px; border-right-width: 0px; border-bottom-width: 0px; border-left-width: 0px; border-style: initial; border-color: initial; outline-width: 0px; outline-style: initial; outline-color: initial; font-weight: inherit; font-style: inherit; font-size: 12px; font-family: inherit; vertical-align: baseline; box-sizing: border-box; border-style: initial; border-color: initial; }.rally-rte-class-0ad16c807{margin-top: 0px; margin-right: 0px; margin-bottom: 0px; margin-left: 0px; padding-top: 0px; padding-right: 0px; padding-bottom: 0px; padding-left: 0px; border-top-width: 0px; border-right-width: 0px; border-bottom-width: 0px; border-left-width: 0px; border-style: initial; border-color: initial; outline-width: 0px; outline-style: initial; outline-color: initial; font-weight: inherit; font-style: inherit; font-size: 14px; font-family: Calibri, sans-serif; vertical-align: baseline; box-sizing: border-box; }.rally-rte-class-023a7f5d2{margin-top: 0px; margin-right: 0px; margin-bottom: 0px; margin-left: 0px; padding-top: 0px; padding-right: 0px; padding-bottom: 0px; padding-left: 0px; border-top-width: 0px; border-right-width: 0px; border-bottom-width: 0px; border-left-width: 0px; border-style: initial; border-color: initial; outline-width: 0px; outline-style: initial; outline-color: initial; font-weight: inherit; font-style: inherit; font-size: 14px; font-family: inherit; vertical-align: baseline; box-sizing: border-box; }.rally-rte-class-0751a6235{margin-top: 0px; margin-right: 0px; margin-bottom: 0px; margin-left: 0px; padding-top: 0px; padding-right: 0px; padding-bottom: 0px; padding-left: 0px; border-top-width: 0px; border-right-width: 0px; border-bottom-width: 0px; border-left-width: 0px; border-style: initial; border-color: initial; outline-width: 0px; outline-style: initial; outline-color: initial; font-weight: inherit; font-style: inherit; font-size: 12px; font-family: inherit; vertical-align: baseline; box-sizing: border-box; text-align: left; }.rally-rte-class-0569815dd{margin-top: 0px; margin-right: 0px; margin-bottom: 0px; margin-left: 0px; padding-top: 0px; padding-right: 0px; padding-bottom: 0px; padding-left: 0px; border-top-width: 0px; border-right-width: 0px; border-bottom-width: 0px; border-left-width: 0px; border-style: initial; border-color: initial; outline-width: 0px; outline-style: initial; outline-color: initial; font-weight: inherit; font-style: inherit; vertical-align: baseline; box-sizing: border-box; }.rally-rte-class-060d80d38{margin-top: 0px; margin-right: 0px; margin-bottom: 0px; margin-left: 0px; padding-top: 0px; padding-right: 0px; padding-bottom: 0px; padding-left: 0px; border-top-width: 0px; border-right-width: 0px; border-bottom-width: 0px; border-left-width: 0px; border-style: initial; border-color: initial; outline-width: 0px; outline-style: initial; outline-color: initial; font-weight: inherit; font-style: inherit; font-size: 12px; font-family: inherit; vertical-align: baseline; box-sizing: border-box; border-collapse: collapse; }.rally-rte-class-0b90b24b{box-sizing: border-box; }&lt;/style&gt;&lt;span class="Apple-style-span rally-rte-class-0ae0d97c9"&gt;&lt;table class="dt-tbl rally-rte-class-090c0c716"&gt;&lt;tbody class="rally-rte-class-050ce70df"&gt;&lt;tr class="rally-rte-class-04b65a1cc"&gt;&lt;td class="rally-rte-class-0c7b83e2f"&gt;&lt;span class="Apple-style-span rally-rte-class-02bd3f8b1"&gt;&lt;table class="dt-tbl rally-rte-class-01229557d"&gt;&lt;tbody class="rally-rte-class-0811e915"&gt;&lt;tr class="rally-rte-class-03e109195"&gt;&lt;td class="rally-rte-class-07c65e01c"&gt;&lt;p class="p1 rally-rte-class-04752fe8d"&gt;Operator steps:&lt;/p&gt;&lt;p class="p1 rally-rte-class-04752fe8d"&gt;1.&amp;nbsp;Add a property to the admin sli.properties&lt;/p&gt;&lt;p class="p1 rally-rte-class-04752fe8d"&gt;&amp;nbsp; &amp;nbsp; &amp;nbsp; properties&lt;/p&gt;&lt;/td&gt;&lt;/tr&gt;&lt;/tbody&gt;&lt;/table&gt;&lt;/span&gt;&lt;span class="Apple-style-span rally-rte-class-0ad16c807"&gt;&lt;div class="rally-rte-class-023a7f5d2"&gt;&amp;nbsp; &amp;nbsp; &amp;nbsp; &amp;nbsp; sli.api.ldap.user&lt;/div&gt;&lt;div class="rally-rte-class-023a7f5d2"&gt;&amp;nbsp; &amp;nbsp; &amp;nbsp; &amp;nbsp; sli.api.ldap.pass&lt;/div&gt;&lt;/span&gt;&lt;div class="rally-rte-class-0751a6235"&gt;&lt;font face="arial, helvetica, sans-serif" class="Apple-style-span rally-rte-class-0569815dd"&gt;&lt;span class="Apple-style-span rally-rte-class-060d80d38"&gt;&lt;b class="rally-rte-class-0b90b24b"&gt;&lt;br class="rally-rte-class-0b90b24b"&gt;&lt;/b&gt;&lt;/span&gt;&lt;/font&gt;&lt;/div&gt;&lt;div class="rally-rte-class-0751a6235"&gt;&lt;font face="arial, helvetica, sans-serif" class="Apple-style-span rally-rte-class-0569815dd"&gt;&lt;span class="Apple-style-span rally-rte-class-060d80d38"&gt;The values for the properties should be the ldap username and password.&lt;/span&gt;&lt;/font&gt;&lt;/div&gt;&lt;/td&gt;&lt;/tr&gt;&lt;/tbody&gt;&lt;/table&gt;&lt;/span&gt;</ReleaseNoteDescription>
    </Defect>
</Objects>